cli.py
compilation.py
grpyc-0.1.3.dist-info/LICENSE
grpyc-0.1.3.dist-info/METADATA
grpyc-0.1.3.dist-info/WHEEL
grpyc-0.1.3.dist-info/entry_points.txt
grpyc-0.1.3.dist-info/top_level.txt
grpyc-0.1.3.dist-info/RECORD
