Metadata-Version: 2.1
Name: grpyc
Version: 0.1.3
Summary: Framework for grpcio (gRPC for python)
Home-page: https://github.com/Gloxounet/gRPyC
Author: gloxounet
License: MIT
Keywords: gRPC framework
Requires-Python: >=3
License-File: LICENSE
Requires-Dist: grpcio-tools (>=1.49.1)
Requires-Dist: Click
